ftl_extract/__init__.py
ftl_extract/__version__.py
ftl_extract/cli.py
ftl_extract/code_extractor.py
ftl_extract/const.py
ftl_extract/exceptions.py
ftl_extract/ftl_extractor.py
ftl_extract/ftl_importer.py
ftl_extract/matcher.py
ftl_extract/py.typed
ftl_extract/utils.py
ftl_extract/process/__init__.py
ftl_extract/process/commentator.py
ftl_extract/process/kwargs_extractor.py
ftl_extract/process/serializer.py
ftl_extract/stub/__init__.py
ftl_extract/stub/generator.py
ftl_extract/stub/tree.py
ftl_extract/stub/utils.py
ftl_extract/stub/visitor.py
ftl_extract-0.9.0.data/scripts/fast-ftl-extract
ftl_extract-0.9.0.dist-info/METADATA
ftl_extract-0.9.0.dist-info/WHEEL
ftl_extract-0.9.0.dist-info/entry_points.txt
ftl_extract-0.9.0.dist-info/top_level.txt
ftl_extract-0.9.0.dist-info/licenses/LICENSE
ftl_extract-0.9.0.dist-info/RECORD
