Metadata-Version: 2.4
Name: FTL-Extract
Version: 0.9.0
Summary: Extract fluent keys from python code and organize them in .ftl files
Author-email: andrew000 <help@kusbot.com>
License-Expression: MIT
Project-URL: Homepage, https://github.com/andrew000/FTL-Extract
Project-URL: Issues, https://github.com/andrew000/FTL-Extract/issues
Project-URL: Repository, https://github.com/andrew000/FTL-Extract
Keywords: i18n,ftl,ftl-extract
Classifier: Programming Language :: Python :: Implementation :: CPython
Classifier: Programming Language :: Rust
Classifier: Programming Language :: Python :: 3
Classifier: Programming Language :: Python :: 3.10
Classifier: Programming Language :: Python :: 3.11
Classifier: Programming Language :: Python :: 3.12
Classifier: Programming Language :: Python :: 3.13
Requires-Python: <3.14,>=3.10
License-File: LICENSE
Requires-Dist: click==8.*
Requires-Dist: fluent-syntax>=0.19
Provides-Extra: dev
Requires-Dist: cibuildwheel==2.23.3; extra == "dev"
Requires-Dist: fluent-runtime==0.4.0; extra == "dev"
Requires-Dist: isort==7.0.0; extra == "dev"
Requires-Dist: mypy==1.18.2; extra == "dev"
Requires-Dist: pre-commit==4.3.0; extra == "dev"
Requires-Dist: ruff==0.14.1; extra == "dev"
Requires-Dist: setuptools-rust==1.12.0; extra == "dev"
Requires-Dist: setuptools==80.9.0; extra == "dev"
Requires-Dist: wheel==0.45.1; extra == "dev"
Provides-Extra: tests
Requires-Dist: coverage==7.11.0; extra == "tests"
Requires-Dist: pytest-cov==7.0.0; extra == "tests"
Requires-Dist: pytest-html==4.1.1; extra == "tests"
Requires-Dist: pytest-mock==3.15.1; extra == "tests"
Requires-Dist: pytest==8.4.2; extra == "tests"
Provides-Extra: docs
Dynamic: license-file
